upsourceapi/__init__.py
upsourceapi/__main__.py
upsourceapi/registry.py
upsourceapi/client/__init__.py
upsourceapi/client/example.py
upsourceapi/client/http_method.py
upsourceapi/client/upsource.py
upsourceapi/model/__init__.py
upsourceapi/model/dto/__init__.py
upsourceapi/model/dto/anchor.py
upsourceapi/model/dto/branch_info.py
upsourceapi/model/dto/branch_merge_info.py
upsourceapi/model/dto/branch_stats.py
upsourceapi/model/dto/can_create_branch_review.py
upsourceapi/model/dto/file_in_revision.py
upsourceapi/model/dto/file_ownership_summary.py
upsourceapi/model/dto/label.py
upsourceapi/model/dto/project_model.py
upsourceapi/model/dto/project_settings.py
upsourceapi/model/dto/range.py
upsourceapi/model/dto/review_id.py
upsourceapi/model/dto/revision_info.py
upsourceapi/model/dto/vcs_configuration.py
upsourceapi/model/dto/vcs_settings.py
upsourceapi/model/enum/__init__.py
upsourceapi/model/enum/ownership_summary.py
upsourceapi/model/enum/revision_reachability.py
upsourceapi/model/enum/revision_state.py
upsourceapi/model/request/__init__.py
upsourceapi/model/request/create_discussion_request.py
upsourceapi/model/request/create_project_request.py
upsourceapi/model/request/create_review_request.py
upsourceapi/model/request/find_projects_request.py
upsourceapi/model/request/get_branch_info_request.py
upsourceapi-0.1.1.dist-info/METADATA
upsourceapi-0.1.1.dist-info/WHEEL
upsourceapi-0.1.1.dist-info/entry_points.txt
upsourceapi-0.1.1.dist-info/top_level.txt
upsourceapi-0.1.1.dist-info/RECORD
