Metadata-Version: 2.1
Name: upsourceapi
Version: 0.1.1
Summary: Upsource API
Home-page: https://github.com/bioinf/alt-code
Author: stepik.org
Author-email: ivan.magda@stepik.org
License: UNKNOWN
Keywords: upsource,api
Platform: UNKNOWN
Classifier: Development Status :: 3 - Alpha
Classifier: Intended Audience :: Developers
Classifier: Topic :: Software Development :: Build Tools
Classifier: License :: OSI Approved :: MIT License
Classifier: Programming Language :: Python :: 3
Classifier: Operating System :: OS Independent
Requires-Python: >=3.0, <4
Requires-Dist: dataclasses
